<?xml version="1.0" encoding="UTF-8" ?>
<odoo>
    <record id="create_po_wizard" model="ir.ui.view">
        <field name="name">create.po.wizard.form</field>
        <field name="model">create_po.wizard</field>
        <field name="arch" type="xml">
            <form string="Create PO">
                <group>
                    <group>
                        <field name="product_id"/>
                        <field name="partner_id"/>
                    </group>
                    <group>
                        <field name="quantity"/>
                        <field name="price"/>
                    </group>
                </group>
                <footer>
                    <button name="action_confirm" string="Confirm" class="btn-primary" type="object"/>
                    <button string="Cancel" class="btn-secondary" special="cancel"/>
                </footer>
            </form>
        </field>
    </record>
</odoo>
